{"settings":[80,60,1,70,50],"leaderboard":[{"score":97011,"playerName":"test4"},{"score":67500,"playerName":"test"},{"score":63501,"playerName":"test"},{"score":64000,"playerName":"test"},{"score":64000,"playerName":"test"},{"score":58506,"playerName":"mike"},{"score":57000,"playerName":"joe"},{"score":63500,"playerName":"test2"},{"score":59000,"playerName":"test2"},{"score":61000,"playerName":"2212"}],"users":[{"skins":[{"cost":0,"name":"Pirate.png","rarity":"Common"},{"cost":0,"name":"Steampunk.png","rarity":"Common"},{"cost":0,"name":"NeonGlow.png","rarity":"Common"},{"cost":0,"name":"AquaticExplorer.png","rarity":"Common"}],"maxLevel":1,"password":"instructor","highScore":0,"currentSkin":{"cost":0,"name":"AquaticExplorer.png","rarity":"Common"},"email":"Null","username":"instructor"},{"skins":[{"cost":0,"name":"Pirate.png","rarity":"Common"},{"cost":0,"name":"Steampunk.png","rarity":"Common"},{"cost":0,"name":"NeonGlow.png","rarity":"Common"},{"cost":0,"name":"AquaticExplorer.png","rarity":"Common"},{"cost":0,"name":"Titanic.png","rarity":"Legendary"}],"maxLevel":25,"password":"debugger","highScore":149024,"currentSkin":{"cost":0,"name":"Titanic.png","rarity":"Legendary"},"email":"Null","username":"debugger"},{"skins":[{"cost":0,"name":"Pirate.png","rarity":"Common"},{"cost":0,"name":"Steampunk.png","rarity":"Common"},{"cost":0,"name":"NeonGlow.png","rarity":"Common"},{"cost":0,"name":"AquaticExplorer.png","rarity":"Common"},{"cost":0,"name":"Titanic.png","rarity":"Legendary"}],"maxLevel":2,"password":"test","highScore":64000,"currentSkin":{"cost":0,"name":"Titanic.png","rarity":"Legendary"},"email":"Null","username":"test"},{"skins":[{"cost":0,"name":"Pirate.png","rarity":"Common"},{"cost":0,"name":"Steampunk.png","rarity":"Common"},{"cost":0,"name":"NeonGlow.png","rarity":"Common"},{"cost":0,"name":"AquaticExplorer.png","rarity":"Common"}],"maxLevel":1,"password":"mike","highScore":0,"currentSkin":{"cost":0,"name":"Pirate.png","rarity":"Common"},"email":"Null","username":"mike"},{"skins":[{"cost":0,"name":"Pirate.png","rarity":"Common"},{"cost":0,"name":"Steampunk.png","rarity":"Common"},{"cost":0,"name":"NeonGlow.png","rarity":"Common"},{"cost":0,"name":"AquaticExplorer.png","rarity":"Common"}],"maxLevel":1,"password":"brian","highScore":0,"currentSkin":{"cost":0,"name":"Pirate.png","rarity":"Common"},"email":"Null","username":"brian"},{"skins":[{"cost":0,"name":"Pirate.png","rarity":"Common"},{"cost":0,"name":"Steampunk.png","rarity":"Common"},{"cost":0,"name":"NeonGlow.png","rarity":"Common"},{"cost":0,"name":"AquaticExplorer.png","rarity":"Common"},{"cost":0,"name":"Titanic.png","rarity":"Legendary"}],"maxLevel":1,"password":"joe","highScore":0,"currentSkin":{"cost":0,"name":"Titanic.png","rarity":"Legendary"},"email":"Null","username":"joe"},{"skins":[{"cost":0,"name":"Pirate.png","rarity":"Common"},{"cost":0,"name":"Steampunk.png","rarity":"Common"},{"cost":0,"name":"NeonGlow.png","rarity":"Common"},{"cost":0,"name":"AquaticExplorer.png","rarity":"Common"}],"maxLevel":2,"password":"test2","highScore":59000,"currentSkin":{"cost":0,"name":"Pirate.png","rarity":"Common"},"email":"Null","username":"test2"},{"skins":[{"cost":0,"name":"Pirate.png","rarity":"Common"},{"cost":0,"name":"Steampunk.png","rarity":"Common"},{"cost":0,"name":"NeonGlow.png","rarity":"Common"},{"cost":0,"name":"AquaticExplorer.png","rarity":"Common"}],"maxLevel":2,"password":"2212","highScore":61000,"currentSkin":{"cost":0,"name":"Pirate.png","rarity":"Common"},"email":"Null","username":"2212"},{"skins":[{"cost":0,"name":"Pirate.png","rarity":"Common"},{"cost":0,"name":"Steampunk.png","rarity":"Common"},{"cost":0,"name":"NeonGlow.png","rarity":"Common"},{"cost":0,"name":"AquaticExplorer.png","rarity":"Common"}],"maxLevel":2,"password":"123","highScore":60500,"currentSkin":{"cost":0,"name":"Pirate.png","rarity":"Common"},"email":"Null","username":"abdullah"}]}